logger_app/__init__.py
logger_app/flask_formatter_rule.py
logger_app/model.py
logger_app-0.0.2.23091422.dist-info/LICENSE
logger_app-0.0.2.23091422.dist-info/METADATA
logger_app-0.0.2.23091422.dist-info/WHEEL
logger_app-0.0.2.23091422.dist-info/top_level.txt
logger_app-0.0.2.23091422.dist-info/RECORD
