Metadata-Version: 2.1
Name: logger-app
Version: 0.0.2.23091422
Summary: 实现对logging的简单扩展
Home-page: https://github.com/BingerYang/logger_app
Author: binger
Author-email: <xuehen_521@126.com>
Maintainer: binger
Maintainer-email: <xuehen_521@126.com>
Platform: all
Requires-Python: >=3.4
License-File: LICENSE
